gym_recsys/__init__.py
gym_recsys/envs/__init__.py
gym_recsys/envs/env.py
gym_recsys/envs/reward_wrappers.py
gym_recsys/envs/slate_space.py
gym_recsys-0.0.3.dist-info/LICENSE
gym_recsys-0.0.3.dist-info/METADATA
gym_recsys-0.0.3.dist-info/WHEEL
gym_recsys-0.0.3.dist-info/top_level.txt
gym_recsys-0.0.3.dist-info/RECORD
